livesync/__init__.py
livesync/apps.py
livesync/asyncserver/__init__.py
livesync/asyncserver/dispatcher.py
livesync/asyncserver/handler.py
livesync/asyncserver/hub.py
livesync/asyncserver/server.py
livesync/core/__init__.py
livesync/core/handler.py
livesync/core/middleware.py
livesync/fswatcher/__init__.py
livesync/fswatcher/handlers.py
livesync/fswatcher/utils.py
livesync/fswatcher/watcher.py
livesync/management/__init__.py
livesync/management/commands/__init__.py
livesync/management/commands/runserver.py
livesync/static/livesync.js
livesync/tests/__init__.py
livesync/tests/test_asyncserver.py
livesync/tests/test_command.py
livesync/tests/test_handlers.py
livesync/tests/test_middleware.py
livesync/tests/test_watchers.py
django3_livesync-1.dist-info/LICENSE
django3_livesync-1.dist-info/METADATA
django3_livesync-1.dist-info/WHEEL
django3_livesync-1.dist-info/top_level.txt
django3_livesync-1.dist-info/RECORD
