Metadata-Version: 2.1
Name: django3-livesync
Version: 1
Summary: TODO
Home-page: https://github.com/Ymil/django-livesync
Author: Fabio Gibson
Author-email: fabiogibson.rj@gmail.com
License: BSD License
Platform: UNKNOWN
Classifier: Environment :: Web Environment
Classifier: Framework :: Django
Classifier: Framework :: Django :: 3.2
Classifier: Intended Audience :: Developers
Classifier: License :: OSI Approved :: BSD License
Classifier: Operating System :: OS Independent
Classifier: Programming Language :: Python
Classifier: Programming Language :: Python :: 3.9
Classifier: Topic :: Internet :: WWW/HTTP
Classifier: Topic :: Internet :: WWW/HTTP :: Dynamic Content
License-File: LICENSE
Requires-Dist: watchdog (>=2.*)
Requires-Dist: tornado (>=6.*)
Requires-Dist: websocket-client (>=1)
